syllarust-0.2.1.dist-info/METADATA
syllarust-0.2.1.dist-info/WHEEL
syllarust-0.2.1.dist-info/licenses/LICENSE
syllarust/__init__.py
syllarust/syllarust.cp311-win32.pyd
syllarust-0.2.1.dist-info/RECORD
