Metadata-Version: 2.4
Name: syllarust
Version: 0.2.1
Classifier: Programming Language :: Rust
Classifier: Programming Language :: Python :: Implementation :: CPython
Classifier: Programming Language :: Python :: Implementation :: PyPy
License-File: LICENSE
Summary: A simple library for quickly counting syllables
Keywords: syllables,NLP,text,language
Author: cyalen
License: Apache-2.0
Requires-Python: >=3.8
Project-URL: Source Code, https://github.com/cyalen/syllarust
